social_auth_wykop
