Metadata-Version: 1.1
Name: social-auth-wykop
Version: 0.0.3
Summary: Wykop backend for python-social-auth.
Home-page: https://github.com/noisy/python-social-auth-wykop
Author: Krzysztof @noisy Szumny
Author-email: noisy.pl@gmail.com
License: LICENSE
Keywords: django social auth oauth2 social-auth wykop wykop.pl
Platform: UNKNOWN
Classifier: Development Status :: 3 - Alpha
Classifier: Intended Audience :: Developers
Classifier: License :: OSI Approved :: MIT License
Classifier: Programming Language :: Python :: 3.6
